langchain_qa_with_references/__init__.py
langchain_qa_with_references/chains/__init__.py
langchain_qa_with_references/chains/qa_with_references/__init__.py
langchain_qa_with_references/chains/qa_with_references/base.py
langchain_qa_with_references/chains/qa_with_references/loading.py
langchain_qa_with_references/chains/qa_with_references/map_reduce_prompts.py
langchain_qa_with_references/chains/qa_with_references/map_rerank_prompts.py
langchain_qa_with_references/chains/qa_with_references/references.py
langchain_qa_with_references/chains/qa_with_references/refine_prompts.py
langchain_qa_with_references/chains/qa_with_references/retrieval.py
langchain_qa_with_references/chains/qa_with_references/stuff_prompt.py
langchain_qa_with_references/chains/qa_with_references_and_verbatims/__init__.py
langchain_qa_with_references/chains/qa_with_references_and_verbatims/base.py
langchain_qa_with_references/chains/qa_with_references_and_verbatims/loading.py
langchain_qa_with_references/chains/qa_with_references_and_verbatims/map_reduce_prompts.py
langchain_qa_with_references/chains/qa_with_references_and_verbatims/map_rerank_prompts.py
langchain_qa_with_references/chains/qa_with_references_and_verbatims/refine_prompts.py
langchain_qa_with_references/chains/qa_with_references_and_verbatims/retrieval.py
langchain_qa_with_references/chains/qa_with_references_and_verbatims/stuff_prompt.py
langchain_qa_with_references/chains/qa_with_references_and_verbatims/verbatims.py
langchain_qa_with_references/chains/retrieval_qa/__init__.py
langchain_qa_with_references/chains/retrieval_qa/base.py
langchain_qa_with_references/chains/retrieval_qa/prompt.py
langchain_qa_with_references-0.0.330.dist-info/METADATA
langchain_qa_with_references-0.0.330.dist-info/WHEEL
langchain_qa_with_references-0.0.330.dist-info/RECORD
