Metadata-Version: 2.1
Name: langchain-qa-with-references
Version: 0.0.330
Summary: This is a temporary project while I wait for my langchain [pull-request](https://github.com/langchain-ai/langchain/pull/7278) to be validated.
Home-page: https://www.github.com/pprados/langchain-qa_with_references
License: Apache 2.0
Author: Philippe PRADOS
Requires-Python: >=3.8.1,<4.0
Classifier: License :: Other/Proprietary License
Classifier: Programming Language :: Python :: 3
Classifier: Programming Language :: Python :: 3.9
Classifier: Programming Language :: Python :: 3.10
Classifier: Programming Language :: Python :: 3.11
Provides-Extra: openai
Requires-Dist: langchain (>=0.0.330)
Requires-Dist: openai (>=0.28,<0.29) ; extra == "openai"
Requires-Dist: tiktoken (>=0.3.2,<0.4.0) ; (python_version >= "3.9" and python_version < "4.0") and (extra == "openai")
Project-URL: Repository, https://www.github.com/pprados/langchain-qa_with_references
